InstrumentAiPdfSplitter/AISplitter.py
InstrumentAiPdfSplitter/__init__.py
instrumentaipdfsplitter-5.2.0.dist-info/licenses/LICENSE
instrumentaipdfsplitter-5.2.0.dist-info/METADATA
instrumentaipdfsplitter-5.2.0.dist-info/WHEEL
instrumentaipdfsplitter-5.2.0.dist-info/top_level.txt
instrumentaipdfsplitter-5.2.0.dist-info/RECORD
