Metadata-Version: 2.4
Name: instrumentaipdfsplitter
Version: 5.2.0
Summary: AI-assisted instrument part detector and PDF splitter
Author-email: Flinn Fuchs <flinn.handymail@gmail.com>
License: Proprietary - No modification allowed
Project-URL: Homepage, https://github.com/DiscoveryFox/InstrumentAiPdfSplitter
Keywords: instrument,pdf,split,splitting,splitting pdf,music,openai
Classifier: Development Status :: 3 - Alpha
Classifier: Intended Audience :: Developers
Classifier: Programming Language :: Python :: 3
Requires-Python: >=3.10
License-File: LICENSE
Requires-Dist: flask>=3.1.2
Requires-Dist: openai>=1.40.0
Requires-Dist: pypdf>=5.0.0
Requires-Dist: pytest>=8.0.0
Requires-Dist: pytest-dotenv>=0.5.2
Requires-Dist: werkzeug>=3.1.3
Dynamic: license-file
